Metadata-Version: 1.2
Name: tanishi
Version: 0.0.6
Summary: First python package
Home-page: UNKNOWN
Author: Himanshu
License: UNKNOWN
Platform: UNKNOWN
Classifier: Programming Language :: Python :: 3
Classifier: License :: OSI Approved :: MIT License
Classifier: Operating System :: OS Independent
Requires-Python: >=3.6
